yutori_mcp/__init__.py
yutori_mcp/client.py
yutori_mcp/formatters.py
yutori_mcp/schemas.py
yutori_mcp/server.py
yutori_mcp-0.1.6.dist-info/METADATA
yutori_mcp-0.1.6.dist-info/WHEEL
yutori_mcp-0.1.6.dist-info/entry_points.txt
yutori_mcp-0.1.6.dist-info/licenses/LICENSE
yutori_mcp-0.1.6.dist-info/RECORD
