Metadata-Version: 2.4
Name: yutori-mcp
Version: 0.1.6
Summary: MCP server for Yutori - web monitoring and browsing automation
Project-URL: Homepage, https://yutori.com
Project-URL: Documentation, https://docs.yutori.com
Project-URL: Repository, https://github.com/yutori-ai/yutori-mcp
Author-email: Yutori <support@yutori.com>
License-Expression: Apache-2.0
License-File: LICENSE
Keywords: browsing,mcp,monitoring,web-automation,yutori
Classifier: Development Status :: 4 - Beta
Classifier: Intended Audience :: Developers
Classifier: License :: OSI Approved :: Apache Software License
Classifier: Programming Language :: Python :: 3
Classifier: Programming Language :: Python :: 3.10
Classifier: Programming Language :: Python :: 3.11
Classifier: Programming Language :: Python :: 3.12
Requires-Python: >=3.10
Requires-Dist: httpx<0.29.0,>=0.26.0
Requires-Dist: mcp>=1.0.0
Requires-Dist: pydantic>=2.0.0
Provides-Extra: dev
Requires-Dist: pytest-asyncio>=0.21.0; extra == 'dev'
Requires-Dist: pytest>=7.0.0; extra == 'dev'
